samplesheetutils/__init__.py
samplesheetutils/binaries/__init__.py
samplesheetutils/binaries/create_samplesheet.py
samplesheetutils/binaries/sample_name.py
samplesheetutils/binaries/truncate_msa.py
samplesheetutils/utils/__init__.py
samplesheetutils/utils/a3m.py
samplesheetutils/utils/alignment.py
samplesheetutils/utils/fasta.py
samplesheetutils/utils/input.py
samplesheetutils/utils/output.py
samplesheetutils/utils/sample.py
samplesheetutils-1.3.4.dist-info/METADATA
samplesheetutils-1.3.4.dist-info/WHEEL
samplesheetutils-1.3.4.dist-info/entry_points.txt
samplesheetutils-1.3.4.dist-info/top_level.txt
samplesheetutils-1.3.4.dist-info/RECORD
