Metadata-Version: 2.1
Name: samplesheetutils
Version: 1.3.4
Summary: Collection of utilities for creating and transforming samplesheets and samples
Home-page: UNKNOWN
Author: nbtm-sh
Author-email: n.glades@unsw.edu.au
License: UNKNOWN
Platform: UNKNOWN
Requires-Dist: pyyaml==6.0.1
